flask_extended/__init__.py
flask_extended-0.2.dist-info/METADATA
flask_extended-0.2.dist-info/WHEEL
flask_extended-0.2.dist-info/top_level.txt
flask_extended-0.2.dist-info/RECORD
